transmorph/__init__.py
transmorph/_logging.py
transmorph/_profiling.py
transmorph/_settings.py
transmorph/datasets/__init__.py
transmorph/datasets/databank_api.py
transmorph/datasets/datasets.json
transmorph/datasets/datasets.py
transmorph/datasets/data/__init__.py
transmorph/datasets/data/spirals/spiralA.csv
transmorph/datasets/data/spirals/spiralA_labels.csv
transmorph/datasets/data/spirals/spiralB.csv
transmorph/datasets/data/spirals/spiralB_labels.csv
transmorph/engine/__init__.py
transmorph/engine/model.py
transmorph/engine/checking/__init__.py
transmorph/engine/checking/checking.py
transmorph/engine/checking/algorithms/__init__.py
transmorph/engine/checking/algorithms/lisi.py
transmorph/engine/checking/algorithms/neighborentropy.py
transmorph/engine/evaluators/__init__.py
transmorph/engine/evaluators/matching_evaluators.py
transmorph/engine/layers/__init__.py
transmorph/engine/layers/layer.py
transmorph/engine/layers/layerchecking.py
transmorph/engine/layers/layerinput.py
transmorph/engine/layers/layermatching.py
transmorph/engine/layers/layermerging.py
transmorph/engine/layers/layeroutput.py
transmorph/engine/layers/layertransformation.py
transmorph/engine/matching/__init__.py
transmorph/engine/matching/matching.py
transmorph/engine/matching/algorithms/__init__.py
transmorph/engine/matching/algorithms/bknn.py
transmorph/engine/matching/algorithms/combinematching.py
transmorph/engine/matching/algorithms/fusedgw.py
transmorph/engine/matching/algorithms/gw.py
transmorph/engine/matching/algorithms/labels.py
transmorph/engine/matching/algorithms/mnn.py
transmorph/engine/matching/algorithms/ot.py
transmorph/engine/merging/__init__.py
transmorph/engine/merging/merging.py
transmorph/engine/merging/algorithms/__init__.py
transmorph/engine/merging/algorithms/barycenter.py
transmorph/engine/merging/algorithms/graphembedding.py
transmorph/engine/merging/algorithms/linearcorrection.py
transmorph/engine/subsampling/__init__.py
transmorph/engine/subsampling/subsampling.py
transmorph-0.2.8.dist-info/LICENSE
transmorph-0.2.8.dist-info/METADATA
transmorph-0.2.8.dist-info/WHEEL
transmorph-0.2.8.dist-info/top_level.txt
transmorph-0.2.8.dist-info/RECORD
