Metadata-Version: 2.1
Name: transmorph
Version: 0.2.8
Summary: A unifying data integration framework.
Home-page: https://github.com/Risitop/transmorph
Author: Aziz Fouché, Loïc Chadoutaud, Andrei Zinovyev (Institut Curie, Paris)
Author-email: aziz.fouche@curie.fr
Classifier: Programming Language :: Python :: 3
Classifier: License :: OSI Approved :: MIT License
Classifier: Operating System :: OS Independent
Requires-Python: >=3.9
License-File: LICENSE
Requires-Dist: anndata (>=0.8.0)
Requires-Dist: cython
Requires-Dist: igraph
Requires-Dist: leidenalg
Requires-Dist: numpy (<1.24,>=1.22)
Requires-Dist: pre-commit
Requires-Dist: pot
Requires-Dist: pymde
Requires-Dist: pynndescent
Requires-Dist: scanpy
Requires-Dist: sccover
Requires-Dist: scikit-learn
Requires-Dist: scipy
Requires-Dist: stabilized-ica (>=2.0)
Requires-Dist: umap-learn
